Smart/giturl.py
Smart/sel-.py
Smart/selq.py
Smart/smart.py
SMSmartPy-1.0.dist-info/METADATA
SMSmartPy-1.0.dist-info/WHEEL
SMSmartPy-1.0.dist-info/top_level.txt
SMSmartPy-1.0.dist-info/RECORD
