Metadata-Version: 2.1
Name: SMSmartPy
Version: 1.0
Summary: A Python package.
Home-page: https://github.com/SmartManoj/SmartPy
Author: Mehul Gupta
Author-email: mehularnavi28@gmail.com
License: MIT
Platform: UNKNOWN
Classifier: License :: OSI Approved :: MIT License
Classifier: Programming Language :: Python :: 3
Classifier: Programming Language :: Python :: 3.7
Requires-Dist: requests
